{
  "protocol_version" : "0.0.6",
  "configuration" : {
    "version" : "(6.12.0) (2020-02/6dd9def57ce)",
    "tlc" : "normal",
    "sigsgev" : "altstack",
    "notifications" : "kqueue",
    "architecture" : "amd64",
    "disabled_features" : "none",
    "smallconfig" : "disabled",
    "bigarrays" : "disabled",
    "softdebug" : "enabled",
    "interpreter" : "enabled",
    "llvm_support" : "disabled",
    "suspend" : "hybrid"
  },
  "memory" : {
    "Resident Size" : "191971328",
    "Virtual Size" : "35364962304",
    "minor_gc_time" : "188933",
    "major_gc_time" : "0",
    "minor_gc_count" : "120",
    "major_gc_count" : "0",
    "major_gc_time_concurrent" : "0"
 },
  "threads" : [
 {
    "is_managed" : true,
    "offset_free_hash" : "0x1224724594",
    "offset_rich_hash" : "0x12247246f7",
    "crashed" : false,
    "native_thread_id" : "0x70000f857000",
    "thread_info_addr" : "0x7fd0eebe5400",
    "thread_name" : "Timer-Scheduler",
    "ctx" : {
      "IP" : "0x7ff804af33ea",
      "SP" : "0x70000f8563d8",
      "BP" : "0x70000f856480"
  },
    "managed_frames" : [
  {
      "is_managed" : "false",
      "native_address" : "unregistered"
   }
,
  {
      "is_managed" : "true",
      "guid" : "55335301-AF77-4FAF-8FC4-0779AFB6F275",
      "token" : "0x00000",
      "native_offset" : "0x0",
      "filename" : "mscorlib.dll",
      "sizeofimage" : "0x44c000",
      "timestamp" : "0x8154c942",
      "il_offset" : "0xffffffff"
   }
,
  {
      "is_managed" : "true",
      "guid" : "55335301-AF77-4FAF-8FC4-0779AFB6F275",
      "token" : "0x6001e95",
      "native_offset" : "0x0",
      "filename" : "mscorlib.dll",
      "sizeofimage" : "0x44c000",
      "timestamp" : "0x8154c942",
      "il_offset" : "0x00044"
   }
,
  {
      "is_managed" : "true",
      "guid" : "55335301-AF77-4FAF-8FC4-0779AFB6F275",
      "token" : "0x6001e81",
      "native_offset" : "0x0",
      "filename" : "mscorlib.dll",
      "sizeofimage" : "0x44c000",
      "timestamp" : "0x8154c942",
      "il_offset" : "0x00014"
   }
,
  {
      "is_managed" : "true",
      "guid" : "55335301-AF77-4FAF-8FC4-0779AFB6F275",
      "token" : "0x6001e80",
      "native_offset" : "0x0",
      "filename" : "mscorlib.dll",
      "sizeofimage" : "0x44c000",
      "timestamp" : "0x8154c942",
      "il_offset" : "0x00000"
   }
,
  {
      "is_managed" : "true",
      "guid" : "55335301-AF77-4FAF-8FC4-0779AFB6F275",
      "token" : "0x6001e7b",
      "native_offset" : "0x0",
      "filename" : "mscorlib.dll",
      "sizeofimage" : "0x44c000",
      "timestamp" : "0x8154c942",
      "il_offset" : "0x00019"
   }
,
  {
      "is_managed" : "true",
      "guid" : "55335301-AF77-4FAF-8FC4-0779AFB6F275",
      "token" : "0x6001e7e",
      "native_offset" : "0x0",
      "filename" : "mscorlib.dll",
      "sizeofimage" : "0x44c000",
      "timestamp" : "0x8154c942",
      "il_offset" : "0x00000"
   }
,
  {
      "is_managed" : "true",
      "guid" : "55335301-AF77-4FAF-8FC4-0779AFB6F275",
      "token" : "0x6001f36",
      "native_offset" : "0x0",
      "filename" : "mscorlib.dll",
      "sizeofimage" : "0x44c000",
      "timestamp" : "0x8154c942",
      "il_offset" : "0x0003c"
   }
,
  {
      "is_managed" : "true",
      "guid" : "55335301-AF77-4FAF-8FC4-0779AFB6F275",
      "token" : "0x6001d63",
      "native_offset" : "0x0",
      "filename" : "mscorlib.dll",
      "sizeofimage" : "0x44c000",
      "timestamp" : "0x8154c942",
      "il_offset" : "0x00014"
   }
,
  {
      "is_managed" : "true",
      "guid" : "55335301-AF77-4FAF-8FC4-0779AFB6F275",
      "token" : "0x6001d0b",
      "native_offset" : "0x0",
      "filename" : "mscorlib.dll",
      "sizeofimage" : "0x44c000",
      "timestamp" : "0x8154c942",
      "il_offset" : "0x00071"
   }
,
  {
      "is_managed" : "true",
      "guid" : "55335301-AF77-4FAF-8FC4-0779AFB6F275",
      "token" : "0x6001d09",
      "native_offset" : "0x0",
      "filename" : "mscorlib.dll",
      "sizeofimage" : "0x44c000",
      "timestamp" : "0x8154c942",
      "il_offset" : "0x00000"
   }
,
  {
      "is_managed" : "true",
      "guid" : "55335301-AF77-4FAF-8FC4-0779AFB6F275",
      "token" : "0x6001d08",
      "native_offset" : "0x0",
      "filename" : "mscorlib.dll",
      "sizeofimage" : "0x44c000",
      "timestamp" : "0x8154c942",
      "il_offset" : "0x0002b"
   }
,
  {
      "is_managed" : "true",
      "guid" : "55335301-AF77-4FAF-8FC4-0779AFB6F275",
      "token" : "0x6001d65",
      "native_offset" : "0x0",
      "filename" : "mscorlib.dll",
      "sizeofimage" : "0x44c000",
      "timestamp" : "0x8154c942",
      "il_offset" : "0x00008"
   }
,
  {
      "is_managed" : "true",
      "guid" : "55335301-AF77-4FAF-8FC4-0779AFB6F275",
      "token" : "0x00000",
      "native_offset" : "0x0",
      "filename" : "mscorlib.dll",
      "sizeofimage" : "0x44c000",
      "timestamp" : "0x8154c942",
      "il_offset" : "0xffffffff"
   }

  ],
  "unmanaged_frames" : [
 {
    "is_managed" : "false",
    "native_address" : "0x10188b4a6",
    "native_offset" : "0x00000"
  }
,
 {
    "is_managed" : "false",
    "native_address" : "0x101a33691",
    "native_offset" : "0x00000"
  }
,
 {
    "is_managed" : "false",
    "native_address" : "0x101a333d7",
    "native_offset" : "0x00000"
  }
,
 {
    "is_managed" : "false",
    "native_address" : "0x10189b800",
    "native_offset" : "0x00000"
  }
,
 {
    "is_managed" : "false",
    "native_address" : "0x7ff804b42dfd",
    "native_offset" : "0x00000"
  }
,
 {
    "is_managed" : "false",
    "native_address" : "unregistered"
  }
,
 {
    "is_managed" : "false",
    "native_address" : "0x101ab5947",
    "native_offset" : "0x00000"
  }
,
 {
    "is_managed" : "false",
    "native_address" : "0x101ab5784",
    "native_offset" : "0x00000"
  }
,
 {
    "is_managed" : "false",
    "native_address" : "0x101a34a4b",
    "native_offset" : "0x00000"
  }
,
 {
    "is_managed" : "false",
    "native_address" : "0x101a2dcb3",
    "native_offset" : "0x00000"
  }
,
 {
    "is_managed" : "false",
    "native_address" : "0x101a2d95f",
    "native_offset" : "0x00000"
  }
,
 {
    "is_managed" : "false",
    "native_address" : "0x101985948",
    "native_offset" : "0x00000"
  }
,
 {
    "is_managed" : "true",
    "guid" : "55335301-AF77-4FAF-8FC4-0779AFB6F275",
    "token" : "0x00000",
    "native_offset" : "0x0",
    "filename" : "mscorlib.dll",
    "sizeofimage" : "0x44c000",
    "timestamp" : "0x8154c942",
    "il_offset" : "0x00000"
  }
,
 {
    "is_managed" : "true",
    "guid" : "55335301-AF77-4FAF-8FC4-0779AFB6F275",
    "token" : "0x6001e95",
    "native_offset" : "0x0",
    "filename" : "mscorlib.dll",
    "sizeofimage" : "0x44c000",
    "timestamp" : "0x8154c942",
    "il_offset" : "0x00000"
  }
,
 {
    "is_managed" : "true",
    "guid" : "55335301-AF77-4FAF-8FC4-0779AFB6F275",
    "token" : "0x6001e81",
    "native_offset" : "0x0",
    "filename" : "mscorlib.dll",
    "sizeofimage" : "0x44c000",
    "timestamp" : "0x8154c942",
    "il_offset" : "0x00000"
  }
,
 {
    "is_managed" : "true",
    "guid" : "55335301-AF77-4FAF-8FC4-0779AFB6F275",
    "token" : "0x6001e80",
    "native_offset" : "0x0",
    "filename" : "mscorlib.dll",
    "sizeofimage" : "0x44c000",
    "timestamp" : "0x8154c942",
    "il_offset" : "0x00000"
  }
,
 {
    "is_managed" : "true",
    "guid" : "55335301-AF77-4FAF-8FC4-0779AFB6F275",
    "token" : "0x6001e7b",
    "native_offset" : "0x0",
    "filename" : "mscorlib.dll",
    "sizeofimage" : "0x44c000",
    "timestamp" : "0x8154c942",
    "il_offset" : "0x00000"
  }
,
 {
    "is_managed" : "true",
    "guid" : "55335301-AF77-4FAF-8FC4-0779AFB6F275",
    "token" : "0x6001e7e",
    "native_offset" : "0x0",
    "filename" : "mscorlib.dll",
    "sizeofimage" : "0x44c000",
    "timestamp" : "0x8154c942",
    "il_offset" : "0x00000"
  }
,
 {
    "is_managed" : "true",
    "guid" : "55335301-AF77-4FAF-8FC4-0779AFB6F275",
    "token" : "0x6001f36",
    "native_offset" : "0x0",
    "filename" : "mscorlib.dll",
    "sizeofimage" : "0x44c000",
    "timestamp" : "0x8154c942",
    "il_offset" : "0x00000"
  }
,
 {
    "is_managed" : "true",
    "guid" : "55335301-AF77-4FAF-8FC4-0779AFB6F275",
    "token" : "0x6001d63",
    "native_offset" : "0x0",
    "filename" : "mscorlib.dll",
    "sizeofimage" : "0x44c000",
    "timestamp" : "0x8154c942",
    "il_offset" : "0x00000"
  }
,
 {
    "is_managed" : "true",
    "guid" : "55335301-AF77-4FAF-8FC4-0779AFB6F275",
    "token" : "0x6001d0b",
    "native_offset" : "0x0",
    "filename" : "mscorlib.dll",
    "sizeofimage" : "0x44c000",
    "timestamp" : "0x8154c942",
    "il_offset" : "0x00000"
  }
,
 {
    "is_managed" : "true",
    "guid" : "55335301-AF77-4FAF-8FC4-0779AFB6F275",
    "token" : "0x6001d09",
    "native_offset" : "0x0",
    "filename" : "mscorlib.dll",
    "sizeofimage" : "0x44c000",
    "timestamp" : "0x8154c942",
    "il_offset" : "0x00000"
  }
,
 {
    "is_managed" : "true",
    "guid" : "55335301-AF77-4FAF-8FC4-0779AFB6F275",
    "token" : "0x6001d08",
    "native_offset" : "0x0",
    "filename" : "mscorlib.dll",
    "sizeofimage" : "0x44c000",
    "timestamp" : "0x8154c942",
    "il_offset" : "0x00000"
  }
,
 {
    "is_managed" : "true",
    "guid" : "55335301-AF77-4FAF-8FC4-0779AFB6F275",
    "token" : "0x6001d65",
    "native_offset" : "0x0",
    "filename" : "mscorlib.dll",
    "sizeofimage" : "0x44c000",
    "timestamp" : "0x8154c942",
    "il_offset" : "0x00000"
  }
,
 {
    "is_managed" : "true",
    "guid" : "55335301-AF77-4FAF-8FC4-0779AFB6F275",
    "token" : "0x00000",
    "native_offset" : "0x0",
    "filename" : "mscorlib.dll",
    "sizeofimage" : "0x44c000",
    "timestamp" : "0x8154c942",
    "il_offset" : "0x00000"
  }
,
 {
    "is_managed" : "false",
    "native_address" : "0x1018a6ee3",
    "native_offset" : "0x00000"
  }
,
 {
    "is_managed" : "false",
    "native_address" : "0x1019db5b8",
    "native_offset" : "0x00000"
  }
,
 {
    "is_managed" : "false",
    "native_address" : "0x1019e1ffd",
    "native_offset" : "0x00000"
  }
,
 {
    "is_managed" : "false",
    "native_address" : "0x101a342b7",
    "native_offset" : "0x00000"
  }
,
 {
    "is_managed" : "false",
    "native_address" : "0x101a3400e",
    "native_offset" : "0x00000"
  }
,
 {
    "is_managed" : "false",
    "native_address" : "0x7ff804b2d4e1",
    "native_offset" : "0x00000"
  }
,
 {
    "is_managed" : "false",
    "native_address" : "0x7ff804b28f6b",
    "native_offset" : "0x00000"
  }

 ]
},
{
  "is_managed" : true,
  "offset_free_hash" : "0x2acd1be6e",
  "offset_rich_hash" : "0x2acd1beb4",
  "crashed" : true,
  "native_thread_id" : "0x1072f5600",
  "thread_info_addr" : "0x7fd0ee808c00",
  "thread_name" : "tid_103",
  "ctx" : {
    "IP" : "0x7ff8049c044e",
    "SP" : "0x7ff7be785528",
    "BP" : "0x7ff7be785560"
 },
  "managed_frames" : [
 {
    "is_managed" : "false",
    "native_address" : "unregistered"
  }
,
 {
    "is_managed" : "true",
    "guid" : "EC064524-B146-4A12-9772-07A7CF94FEDE",
    "token" : "0x00000",
    "native_offset" : "0x0",
    "filename" : "Xamarin.Mac.dll",
    "sizeofimage" : "0x1a30000",
    "timestamp" : "0xe51bcc97",
    "il_offset" : "0xffffffff"
  }
,
 {
    "is_managed" : "true",
    "guid" : "EC064524-B146-4A12-9772-07A7CF94FEDE",
    "token" : "0x60108ec",
    "native_offset" : "0x0",
    "filename" : "Xamarin.Mac.dll",
    "sizeofimage" : "0x1a30000",
    "timestamp" : "0xe51bcc97",
    "il_offset" : "0x00040"
  }
,
 {
    "is_managed" : "true",
    "guid" : "6C569072-A5AF-4C16-B484-85194BC6B4EF",
    "token" : "0x6000001",
    "native_offset" : "0x0",
    "filename" : "SimpleChat.exe",
    "sizeofimage" : "0x12000",
    "timestamp" : "0x63d660e2",
    "il_offset" : "0x00008"
  }
,
 {
    "is_managed" : "true",
    "guid" : "6C569072-A5AF-4C16-B484-85194BC6B4EF",
    "token" : "0x00000",
    "native_offset" : "0x0",
    "filename" : "SimpleChat.exe",
    "sizeofimage" : "0x12000",
    "timestamp" : "0x63d660e2",
    "il_offset" : "0xffffffff"
  }

 ],
"unmanaged_frames" : [
{
  "is_managed" : "false",
  "native_address" : "0x10188b4a6",
  "native_offset" : "0x00000"
 }
,
{
  "is_managed" : "false",
  "native_address" : "0x101a33691",
  "native_offset" : "0x00000"
 }
,
{
  "is_managed" : "false",
  "native_address" : "0x101a33cc6",
  "native_offset" : "0x00000"
 }
,
{
  "is_managed" : "false",
  "native_address" : "0x10189c85b",
  "native_offset" : "0x00000"
 }
,
{
  "is_managed" : "false",
  "native_address" : "0x1018900fe",
  "native_offset" : "0x00000"
 }
,
{
  "is_managed" : "false",
  "native_address" : "0x101b587e7",
  "native_offset" : "0x00000"
 }
,
{
  "is_managed" : "false",
  "native_address" : "0x10180bf4e",
  "native_offset" : "0x00000"
 }
,
{
  "is_managed" : "false",
  "native_address" : "0x7ff8049c044e",
  "native_offset" : "0x00000"
 }
,
{
  "is_managed" : "false",
  "native_address" : "0x7ff80766013f",
  "native_offset" : "0x00000"
 }
,
{
  "is_managed" : "false",
  "native_address" : "0x7ff80765ffa2",
  "native_offset" : "0x00000"
 }
,
{
  "is_managed" : "false",
  "native_address" : "0x7ff80765fe51",
  "native_offset" : "0x00000"
 }
,
{
  "is_managed" : "false",
  "native_address" : "0x7ff80765fe00",
  "native_offset" : "0x00000"
 }
,
{
  "is_managed" : "false",
  "native_address" : "0x7ff807ab21e2",
  "native_offset" : "0x00000"
 }
,
{
  "is_managed" : "false",
  "native_address" : "0x7ff807797713",
  "native_offset" : "0x00000"
 }
,
{
  "is_managed" : "false",
  "native_address" : "0x7ff80761905b",
  "native_offset" : "0x00000"
 }
,
{
  "is_managed" : "false",
  "native_address" : "0x7ff80779744d",
  "native_offset" : "0x00000"
 }
,
{
  "is_managed" : "false",
  "native_address" : "0x7ff807aa8dd0",
  "native_offset" : "0x00000"
 }
,
{
  "is_managed" : "false",
  "native_address" : "0x7ff80779757c",
  "native_offset" : "0x00000"
 }
,
{
  "is_managed" : "false",
  "native_address" : "0x7ff80779757c",
  "native_offset" : "0x00000"
 }
,
{
  "is_managed" : "false",
  "native_address" : "0x7ff80800b137",
  "native_offset" : "0x00000"
 }
,
{
  "is_managed" : "false",
  "native_address" : "0x7ff80779757c",
  "native_offset" : "0x00000"
 }
,
{
  "is_managed" : "false",
  "native_address" : "0x7ff8077cf265",
  "native_offset" : "0x00000"
 }
,
{
  "is_managed" : "false",
  "native_address" : "0x7ff807762991",
  "native_offset" : "0x00000"
 }
,
{
  "is_managed" : "false",
  "native_address" : "0x7ff8077ccc1b",
  "native_offset" : "0x00000"
 }
,
{
  "is_managed" : "false",
  "native_address" : "0x7ff8077cadca",
  "native_offset" : "0x00000"
 }
,
{
  "is_managed" : "false",
  "native_address" : "0x7ff80779bf3c",
  "native_offset" : "0x00000"
 }
,
{
  "is_managed" : "false",
  "native_address" : "0x7ff807a5418b",
  "native_offset" : "0x00000"
 }
,
{
  "is_managed" : "false",
  "native_address" : "0x7ff80761cd3e",
  "native_offset" : "0x00000"
 }
,
{
  "is_managed" : "false",
  "native_address" : "0x7ff8075f0c97",
  "native_offset" : "0x00000"
 }
,
{
  "is_managed" : "true",
  "guid" : "EC064524-B146-4A12-9772-07A7CF94FEDE",
  "token" : "0x00000",
  "native_offset" : "0x0",
  "filename" : "Xamarin.Mac.dll",
  "sizeofimage" : "0x1a30000",
  "timestamp" : "0xe51bcc97",
  "il_offset" : "0x00000"
 }
,
{
  "is_managed" : "true",
  "guid" : "EC064524-B146-4A12-9772-07A7CF94FEDE",
  "token" : "0x60108ec",
  "native_offset" : "0x0",
  "filename" : "Xamarin.Mac.dll",
  "sizeofimage" : "0x1a30000",
  "timestamp" : "0xe51bcc97",
  "il_offset" : "0x00000"
 }
,
{
  "is_managed" : "true",
  "guid" : "6C569072-A5AF-4C16-B484-85194BC6B4EF",
  "token" : "0x6000001",
  "native_offset" : "0x0",
  "filename" : "SimpleChat.exe",
  "sizeofimage" : "0x12000",
  "timestamp" : "0x63d660e2",
  "il_offset" : "0x00000"
 }
,
{
  "is_managed" : "true",
  "guid" : "6C569072-A5AF-4C16-B484-85194BC6B4EF",
  "token" : "0x00000",
  "native_offset" : "0x0",
  "filename" : "SimpleChat.exe",
  "sizeofimage" : "0x12000",
  "timestamp" : "0x63d660e2",
  "il_offset" : "0x00000"
 }
,
{
  "is_managed" : "false",
  "native_address" : "0x1018a6ee3",
  "native_offset" : "0x00000"
 }
,
{
  "is_managed" : "false",
  "native_address" : "0x1019db5b8",
  "native_offset" : "0x00000"
 }
,
{
  "is_managed" : "false",
  "native_address" : "0x1019e29d5",
  "native_offset" : "0x00000"
 }
,
{
  "is_managed" : "false",
  "native_address" : "0x101801d7c",
  "native_offset" : "0x00000"
 }
,
{
  "is_managed" : "false",
  "native_address" : "0x101804e18",
  "native_offset" : "0x00000"
 }
,
{
  "is_managed" : "false",
  "native_address" : "0x1017ba653",
  "native_offset" : "0x00000"
 }
,
{
  "is_managed" : "false",
  "native_address" : "0x1017bb464",
  "native_offset" : "0x00000"
 }
,
{
  "is_managed" : "false",
  "native_address" : "0x10727a52e",
  "native_offset" : "0x00000"
 }

]
},
{
"is_managed" : false,
"offset_free_hash" : "0x0",
"offset_rich_hash" : "0x0",
"crashed" : false,
"native_thread_id" : "0x70000df9b000",
"thread_info_addr" : "0x7fd0ee80b000",
"thread_name" : "Finalizer",
"ctx" : {
  "IP" : "0x7ff804af09b6",
  "SP" : "0x70000df9ae98",
  "BP" : "0x70000df9aee0"
},
"unmanaged_frames" : [
{
  "is_managed" : "false",
  "native_address" : "0x10188b4a6",
  "native_offset" : "0x00000"
 }
,
{
  "is_managed" : "false",
  "native_address" : "0x101a33691",
  "native_offset" : "0x00000"
 }
,
{
  "is_managed" : "false",
  "native_address" : "0x101a333d7",
  "native_offset" : "0x00000"
 }
,
{
  "is_managed" : "false",
  "native_address" : "0x10189b800",
  "native_offset" : "0x00000"
 }
,
{
  "is_managed" : "false",
  "native_address" : "0x7ff804b42dfd",
  "native_offset" : "0x00000"
 }
,
{
  "is_managed" : "false",
  "native_address" : "0x7fd0ec704280",
  "native_offset" : "0x00000"
 }
,
{
  "is_managed" : "false",
  "native_address" : "0x101a341c3",
  "native_offset" : "0x00000"
 }
,
{
  "is_managed" : "false",
  "native_address" : "0x101a3400e",
  "native_offset" : "0x00000"
 }
,
{
  "is_managed" : "false",
  "native_address" : "0x7ff804b2d4e1",
  "native_offset" : "0x00000"
 }
,
{
  "is_managed" : "false",
  "native_address" : "0x7ff804b28f6b",
  "native_offset" : "0x00000"
 }

]
},
{
"is_managed" : true,
"offset_free_hash" : "0x137adcddbe",
"offset_rich_hash" : "0x137adcdf98",
"crashed" : false,
"native_thread_id" : "0x70000ee48000",
"thread_info_addr" : "0x7fd0ed0d2e00",
"thread_name" : "Thread Pool Worker",
"ctx" : {
  "IP" : "0x7ff804af33ea",
  "SP" : "0x70000ee47238",
  "BP" : "0x70000ee472e0"
},
"managed_frames" : [
{
  "is_managed" : "false",
  "native_address" : "unregistered"
 }
,
{
  "is_managed" : "true",
  "guid" : "55335301-AF77-4FAF-8FC4-0779AFB6F275",
  "token" : "0x00000",
  "native_offset" : "0x0",
  "filename" : "mscorlib.dll",
  "sizeofimage" : "0x44c000",
  "timestamp" : "0x8154c942",
  "il_offset" : "0xffffffff"
 }
,
{
  "is_managed" : "true",
  "guid" : "55335301-AF77-4FAF-8FC4-0779AFB6F275",
  "token" : "0x00000",
  "native_offset" : "0x0",
  "filename" : "mscorlib.dll",
  "sizeofimage" : "0x44c000",
  "timestamp" : "0x8154c942",
  "il_offset" : "0xffffffff"
 }
,
{
  "is_managed" : "true",
  "guid" : "6C569072-A5AF-4C16-B484-85194BC6B4EF",
  "token" : "0x600006f",
  "native_offset" : "0x0",
  "filename" : "SimpleChat.exe",
  "sizeofimage" : "0x12000",
  "timestamp" : "0x63d660e2",
  "il_offset" : "0x00055"
 }
,
{
  "is_managed" : "true",
  "guid" : "55335301-AF77-4FAF-8FC4-0779AFB6F275",
  "token" : "0x60021d9",
  "native_offset" : "0x0",
  "filename" : "mscorlib.dll",
  "sizeofimage" : "0x44c000",
  "timestamp" : "0x8154c942",
  "il_offset" : "0x0000f"
 }
,
{
  "is_managed" : "true",
  "guid" : "55335301-AF77-4FAF-8FC4-0779AFB6F275",
  "token" : "0x60021d5",
  "native_offset" : "0x0",
  "filename" : "mscorlib.dll",
  "sizeofimage" : "0x44c000",
  "timestamp" : "0x8154c942",
  "il_offset" : "0x00000"
 }
,
{
  "is_managed" : "true",
  "guid" : "55335301-AF77-4FAF-8FC4-0779AFB6F275",
  "token" : "0x60021d8",
  "native_offset" : "0x0",
  "filename" : "mscorlib.dll",
  "sizeofimage" : "0x44c000",
  "timestamp" : "0x8154c942",
  "il_offset" : "0x00006"
 }
,
{
  "is_managed" : "true",
  "guid" : "55335301-AF77-4FAF-8FC4-0779AFB6F275",
  "token" : "0x6001d0b",
  "native_offset" : "0x0",
  "filename" : "mscorlib.dll",
  "sizeofimage" : "0x44c000",
  "timestamp" : "0x8154c942",
  "il_offset" : "0x00071"
 }
,
{
  "is_managed" : "true",
  "guid" : "55335301-AF77-4FAF-8FC4-0779AFB6F275",
  "token" : "0x6001d09",
  "native_offset" : "0x0",
  "filename" : "mscorlib.dll",
  "sizeofimage" : "0x44c000",
  "timestamp" : "0x8154c942",
  "il_offset" : "0x00000"
 }
,
{
  "is_managed" : "true",
  "guid" : "55335301-AF77-4FAF-8FC4-0779AFB6F275",
  "token" : "0x6002241",
  "native_offset" : "0x0",
  "filename" : "mscorlib.dll",
  "sizeofimage" : "0x44c000",
  "timestamp" : "0x8154c942",
  "il_offset" : "0x00034"
 }
,
{
  "is_managed" : "true",
  "guid" : "55335301-AF77-4FAF-8FC4-0779AFB6F275",
  "token" : "0x60021d7",
  "native_offset" : "0x0",
  "filename" : "mscorlib.dll",
  "sizeofimage" : "0x44c000",
  "timestamp" : "0x8154c942",
  "il_offset" : "0x0004a"
 }
,
{
  "is_managed" : "true",
  "guid" : "55335301-AF77-4FAF-8FC4-0779AFB6F275",
  "token" : "0x60021d6",
  "native_offset" : "0x0",
  "filename" : "mscorlib.dll",
  "sizeofimage" : "0x44c000",
  "timestamp" : "0x8154c942",
  "il_offset" : "0x00000"
 }
,
{
  "is_managed" : "true",
  "guid" : "55335301-AF77-4FAF-8FC4-0779AFB6F275",
  "token" : "0x6001e13",
  "native_offset" : "0x0",
  "filename" : "mscorlib.dll",
  "sizeofimage" : "0x44c000",
  "timestamp" : "0x8154c942",
  "il_offset" : "0x00074"
 }
,
{
  "is_managed" : "true",
  "guid" : "EC064524-B146-4A12-9772-07A7CF94FEDE",
  "token" : "0x6016866",
  "native_offset" : "0x0",
  "filename" : "Xamarin.Mac.dll",
  "sizeofimage" : "0x1a30000",
  "timestamp" : "0xe51bcc97",
  "il_offset" : "0x00007"
 }
,
{
  "is_managed" : "true",
  "guid" : "55335301-AF77-4FAF-8FC4-0779AFB6F275",
  "token" : "0x6001e29",
  "native_offset" : "0x0",
  "filename" : "mscorlib.dll",
  "sizeofimage" : "0x44c000",
  "timestamp" : "0x8154c942",
  "il_offset" : "0x00009"
 }
,
{
  "is_managed" : "true",
  "guid" : "55335301-AF77-4FAF-8FC4-0779AFB6F275",
  "token" : "0x00000",
  "native_offset" : "0x0",
  "filename" : "mscorlib.dll",
  "sizeofimage" : "0x44c000",
  "timestamp" : "0x8154c942",
  "il_offset" : "0xffffffff"
 }

],
"unmanaged_frames" : [
{
"is_managed" : "false",
"native_address" : "0x10188b4a6",
"native_offset" : "0x00000"
}
,
{
"is_managed" : "false",
"native_address" : "0x101a33691",
"native_offset" : "0x00000"
}
,
{
"is_managed" : "false",
"native_address" : "0x101a333d7",
"native_offset" : "0x00000"
}
,
{
"is_managed" : "false",
"native_address" : "0x10189b800",
"native_offset" : "0x00000"
}
,
{
"is_managed" : "false",
"native_address" : "0x7ff804b42dfd",
"native_offset" : "0x00000"
}
,
{
"is_managed" : "false",
"native_address" : "0x102233000",
"native_offset" : "0x00000"
}
,
{
"is_managed" : "false",
"native_address" : "0x101ab5947",
"native_offset" : "0x00000"
}
,
{
"is_managed" : "false",
"native_address" : "0x101ab5784",
"native_offset" : "0x00000"
}
,
{
"is_managed" : "false",
"native_address" : "0x101a34a4b",
"native_offset" : "0x00000"
}
,
{
"is_managed" : "false",
"native_address" : "0x101a2dcb3",
"native_offset" : "0x00000"
}
,
{
"is_managed" : "false",
"native_address" : "0x101a3497d",
"native_offset" : "0x00000"
}
,
{
"is_managed" : "false",
"native_address" : "0x101a324ba",
"native_offset" : "0x00000"
}
,
{
"is_managed" : "true",
"guid" : "55335301-AF77-4FAF-8FC4-0779AFB6F275",
"token" : "0x00000",
"native_offset" : "0x0",
"filename" : "mscorlib.dll",
"sizeofimage" : "0x44c000",
"timestamp" : "0x8154c942",
"il_offset" : "0x00000"
}
,
{
"is_managed" : "true",
"guid" : "55335301-AF77-4FAF-8FC4-0779AFB6F275",
"token" : "0x00000",
"native_offset" : "0x0",
"filename" : "mscorlib.dll",
"sizeofimage" : "0x44c000",
"timestamp" : "0x8154c942",
"il_offset" : "0x00000"
}
,
{
"is_managed" : "true",
"guid" : "6C569072-A5AF-4C16-B484-85194BC6B4EF",
"token" : "0x600006f",
"native_offset" : "0x0",
"filename" : "SimpleChat.exe",
"sizeofimage" : "0x12000",
"timestamp" : "0x63d660e2",
"il_offset" : "0x00000"
}
,
{
"is_managed" : "true",
"guid" : "55335301-AF77-4FAF-8FC4-0779AFB6F275",
"token" : "0x60021d9",
"native_offset" : "0x0",
"filename" : "mscorlib.dll",
"sizeofimage" : "0x44c000",
"timestamp" : "0x8154c942",
"il_offset" : "0x00000"
}
,
{
"is_managed" : "true",
"guid" : "55335301-AF77-4FAF-8FC4-0779AFB6F275",
"token" : "0x60021d5",
"native_offset" : "0x0",
"filename" : "mscorlib.dll",
"sizeofimage" : "0x44c000",
"timestamp" : "0x8154c942",
"il_offset" : "0x00000"
}
,
{
"is_managed" : "true",
"guid" : "55335301-AF77-4FAF-8FC4-0779AFB6F275",
"token" : "0x60021d8",
"native_offset" : "0x0",
"filename" : "mscorlib.dll",
"sizeofimage" : "0x44c000",
"timestamp" : "0x8154c942",
"il_offset" : "0x00000"
}
,
{
"is_managed" : "true",
"guid" : "55335301-AF77-4FAF-8FC4-0779AFB6F275",
"token" : "0x6001d0b",
"native_offset" : "0x0",
"filename" : "mscorlib.dll",
"sizeofimage" : "0x44c000",
"timestamp" : "0x8154c942",
"il_offset" : "0x00000"
}
,
{
"is_managed" : "true",
"guid" : "55335301-AF77-4FAF-8FC4-0779AFB6F275",
"token" : "0x6001d09",
"native_offset" : "0x0",
"filename" : "mscorlib.dll",
"sizeofimage" : "0x44c000",
"timestamp" : "0x8154c942",
"il_offset" : "0x00000"
}
,
{
"is_managed" : "true",
"guid" : "55335301-AF77-4FAF-8FC4-0779AFB6F275",
"token" : "0x6002241",
"native_offset" : "0x0",
"filename" : "mscorlib.dll",
"sizeofimage" : "0x44c000",
"timestamp" : "0x8154c942",
"il_offset" : "0x00000"
}
,
{
"is_managed" : "true",
"guid" : "55335301-AF77-4FAF-8FC4-0779AFB6F275",
"token" : "0x60021d7",
"native_offset" : "0x0",
"filename" : "mscorlib.dll",
"sizeofimage" : "0x44c000",
"timestamp" : "0x8154c942",
"il_offset" : "0x00000"
}
,
{
"is_managed" : "true",
"guid" : "55335301-AF77-4FAF-8FC4-0779AFB6F275",
"token" : "0x60021d6",
"native_offset" : "0x0",
"filename" : "mscorlib.dll",
"sizeofimage" : "0x44c000",
"timestamp" : "0x8154c942",
"il_offset" : "0x00000"
}
,
{
"is_managed" : "true",
"guid" : "55335301-AF77-4FAF-8FC4-0779AFB6F275",
"token" : "0x6001e13",
"native_offset" : "0x0",
"filename" : "mscorlib.dll",
"sizeofimage" : "0x44c000",
"timestamp" : "0x8154c942",
"il_offset" : "0x00000"
}
,
{
"is_managed" : "true",
"guid" : "EC064524-B146-4A12-9772-07A7CF94FEDE",
"token" : "0x6016866",
"native_offset" : "0x0",
"filename" : "Xamarin.Mac.dll",
"sizeofimage" : "0x1a30000",
"timestamp" : "0xe51bcc97",
"il_offset" : "0x00000"
}
,
{
"is_managed" : "true",
"guid" : "55335301-AF77-4FAF-8FC4-0779AFB6F275",
"token" : "0x6001e29",
"native_offset" : "0x0",
"filename" : "mscorlib.dll",
"sizeofimage" : "0x44c000",
"timestamp" : "0x8154c942",
"il_offset" : "0x00000"
}
,
{
"is_managed" : "true",
"guid" : "55335301-AF77-4FAF-8FC4-0779AFB6F275",
"token" : "0x00000",
"native_offset" : "0x0",
"filename" : "mscorlib.dll",
"sizeofimage" : "0x44c000",
"timestamp" : "0x8154c942",
"il_offset" : "0x00000"
}
,
{
"is_managed" : "false",
"native_address" : "0x1018a6ee3",
"native_offset" : "0x00000"
}
,
{
"is_managed" : "false",
"native_address" : "0x1019dcfbf",
"native_offset" : "0x00000"
}
,
{
"is_managed" : "false",
"native_address" : "0x101a2a1aa",
"native_offset" : "0x00000"
}
,
{
"is_managed" : "false",
"native_address" : "0x101a27e01",
"native_offset" : "0x00000"
}
,
{
"is_managed" : "false",
"native_address" : "0x101a341c3",
"native_offset" : "0x00000"
}
,
{
"is_managed" : "false",
"native_address" : "0x101a3400e",
"native_offset" : "0x00000"
}
,
{
"is_managed" : "false",
"native_address" : "0x7ff804b2d4e1",
"native_offset" : "0x00000"
}
,
{
"is_managed" : "false",
"native_address" : "0x7ff804b28f6b",
"native_offset" : "0x00000"
}

]
},
{
"is_managed" : true,
"offset_free_hash" : "0x2df1d21b2",
"offset_rich_hash" : "0x2df1d21b1",
"crashed" : false,
"native_thread_id" : "0x70000e42d000",
"thread_info_addr" : "0x7fd0eeb0f200",
"thread_name" : "tid_12f03",
"ctx" : {
"IP" : "0x7ff804af33ea",
"SP" : "0x70000e42c0f8",
"BP" : "0x70000e42c1a0"
},
"managed_frames" : [
{
"is_managed" : "false",
"native_address" : "unregistered"
}
,
{
"is_managed" : "true",
"guid" : "55335301-AF77-4FAF-8FC4-0779AFB6F275",
"token" : "0x00000",
"native_offset" : "0x0",
"filename" : "mscorlib.dll",
"sizeofimage" : "0x44c000",
"timestamp" : "0x8154c942",
"il_offset" : "0xffffffff"
}
,
{
"is_managed" : "true",
"guid" : "2EA1C41C-6803-40DA-A252-3FE5E7EF9CCF",
"token" : "0x600012e",
"native_offset" : "0x0",
"filename" : "mylibztmac.dll",
"sizeofimage" : "0x14000",
"timestamp" : "0x63d660df",
"il_offset" : "0x00001"
}
,
{
"is_managed" : "true",
"guid" : "2EA1C41C-6803-40DA-A252-3FE5E7EF9CCF",
"token" : "0x00000",
"native_offset" : "0x0",
"filename" : "mylibztmac.dll",
"sizeofimage" : "0x14000",
"timestamp" : "0x63d660df",
"il_offset" : "0xffffffff"
}

],
"unmanaged_frames" : [
{
"is_managed" : "false",
"native_address" : "0x10188b4a6",
"native_offset" : "0x00000"
}
,
{
"is_managed" : "false",
"native_address" : "0x101a33691",
"native_offset" : "0x00000"
}
,
{
"is_managed" : "false",
"native_address" : "0x101a333d7",
"native_offset" : "0x00000"
}
,
{
"is_managed" : "false",
"native_address" : "0x10189b800",
"native_offset" : "0x00000"
}
,
{
"is_managed" : "false",
"native_address" : "0x7ff804b42dfd",
"native_offset" : "0x00000"
}
,
{
"is_managed" : "false",
"native_address" : "0x19",
"native_offset" : "0x00000"
}
,
{
"is_managed" : "false",
"native_address" : "0x101ab5947",
"native_offset" : "0x00000"
}
,
{
"is_managed" : "false",
"native_address" : "0x101ab5784",
"native_offset" : "0x00000"
}
,
{
"is_managed" : "false",
"native_address" : "0x101a34a4b",
"native_offset" : "0x00000"
}
,
{
"is_managed" : "false",
"native_address" : "0x101a2dcb3",
"native_offset" : "0x00000"
}
,
{
"is_managed" : "false",
"native_address" : "0x101a3497d",
"native_offset" : "0x00000"
}
,
{
"is_managed" : "true",
"guid" : "(null)",
"token" : "0x00000",
"native_offset" : "0x0",
"filename" : "(null)",
"sizeofimage" : "0x0",
"timestamp" : "0x0",
"il_offset" : "0x00000"
}
,
{
"is_managed" : "true",
"guid" : "2EA1C41C-6803-40DA-A252-3FE5E7EF9CCF",
"token" : "0x00000",
"native_offset" : "0x0",
"filename" : "mylibztmac.dll",
"sizeofimage" : "0x14000",
"timestamp" : "0x63d660df",
"il_offset" : "0x00000"
}
,
{
"is_managed" : "false",
"native_address" : "0x1018a6ee3",
"native_offset" : "0x00000"
}
,
{
"is_managed" : "false",
"native_address" : "0x1019db5b8",
"native_offset" : "0x00000"
}
,
{
"is_managed" : "false",
"native_address" : "0x1019ac2de",
"native_offset" : "0x00000"
}
,
{
"is_managed" : "false",
"native_address" : "0x10197f9d3",
"native_offset" : "0x00000"
}
,
{
"is_managed" : "true",
"guid" : "55335301-AF77-4FAF-8FC4-0779AFB6F275",
"token" : "0x00000",
"native_offset" : "0x0",
"filename" : "mscorlib.dll",
"sizeofimage" : "0x44c000",
"timestamp" : "0x8154c942",
"il_offset" : "0x00000"
}
,
{
"is_managed" : "true",
"guid" : "2EA1C41C-6803-40DA-A252-3FE5E7EF9CCF",
"token" : "0x600012e",
"native_offset" : "0x0",
"filename" : "mylibztmac.dll",
"sizeofimage" : "0x14000",
"timestamp" : "0x63d660df",
"il_offset" : "0x00000"
}
,
{
"is_managed" : "true",
"guid" : "2EA1C41C-6803-40DA-A252-3FE5E7EF9CCF",
"token" : "0x00000",
"native_offset" : "0x0",
"filename" : "mylibztmac.dll",
"sizeofimage" : "0x14000",
"timestamp" : "0x63d660df",
"il_offset" : "0x00000"
}
,
{
"is_managed" : "false",
"native_address" : "0x102345b67",
"native_offset" : "0x00000"
}
,
{
"is_managed" : "false",
"native_address" : "0x102344550",
"native_offset" : "0x00000"
}
,
{
"is_managed" : "false",
"native_address" : "0x7ff804b2d4e1",
"native_offset" : "0x00000"
}
,
{
"is_managed" : "false",
"native_address" : "0x7ff804b28f6b",
"native_offset" : "0x00000"
}

]
}
]
}